{"title":"엘르 코리아 ─ 스타","url":"https://www.elle.co.kr/star","favicon":"https://www.elle.co.kr/favicon.ico","elements":[{"title":"이제 남친짤 아닌 남편짤 생성기! 윤박X김수빈 럽스타그램","contents":"","link":"https://www.elle.co.kr/article/84397","retrieved":1708623574807},{"title":"한국 알뜰하게 즐기는 중! 티모시 샬라메-젠데이아 콜먼 내한 스케줄","contents":"","link":"https://www.elle.co.kr/article/84396","retrieved":1708623574807},{"title":"아이유가 샤라웃한 유튜버 '청계산댕이레코즈'는 누구?","contents":"","link":"https://www.elle.co.kr/article/84391","retrieved":1708623574809},{"title":"직접 찾아와 사과한 이강인의 뉘우침에 손흥민이 보인 반응.txt","contents":"그릇 사이즈 레전드.","link":"https://www.elle.co.kr/article/84389","retrieved":1708580391797},{"title":"이무생의 느와르","contents":"&lt;마에스트라&gt;로 또한번 인생캐릭터 경신한 이무생.","link":"https://www.elle.co.kr/article/84381","retrieved":1708537184945},{"title":"매혹적이고 우아한, 로운","contents":"밀라노에 등장한 로운의 이토록 다양한 면면.","link":"https://www.elle.co.kr/article/84362","retrieved":1708537184946},{"title":"위태롭게 일렁이다가 금세 단단하고 아름다워지는 하현상","contents":"EP 4집 <with all=\"\" my=\"\" heart=\"\">로 돌아온 그를 만나 보았다.                                     </with>","link":"https://www.elle.co.kr/article/84355","retrieved":1708537184948},{"title":"FT아일랜드 송승현이 연예계 은퇴를 선언한 이유","contents":"","link":"https://www.elle.co.kr/article/84384","retrieved":1708537184951}]}