{"title":"엘르 코리아 ─ 스타","url":"https://www.elle.co.kr/star","favicon":"https://www.elle.co.kr/favicon.ico","elements":[{"title":"이준호, <엘르> 디 에디션(D Edition) 10월 커버 공개 #ELLE_D에디션","contents":"이준호, 새로운 남성미의 정립.","link":"https://www.elle.co.kr/article/81168","retrieved":1696657218006},{"title":"로컬 맛집부터 쇼핑까지! 윤승아 따라 연희동 한 바퀴.list","contents":"이번 주말, 느긋하게 쇼핑하면서 커피 한 잔의 여유를 즐기고 싶다면 윤승아의 발자취를 따라 ...","link":"https://www.elle.co.kr/article/81167","retrieved":1696614009127},{"title":"부국제 레드카펫에서도 빛난 정수정, 요즘 푹 빠진 최애 운동은? #스타다이어트","contents":"","link":"https://www.elle.co.kr/article/81155","retrieved":1696614009131},{"title":"유빈이 권순우와 결별 후 직접 전한 심경 (ft.럽스타 삭제)","contents":"","link":"https://www.elle.co.kr/article/81133","retrieved":1696614009133},{"title":"함정을 찾아라! 스타들의 AI 이어북 모음.zip","contents":"설마 아직도 안 해본 건 아니죠?","link":"https://www.elle.co.kr/article/81130","retrieved":1696570806328},{"title":"디즈니+ 계정 공유 막고, 넷플릭스 가격 올린다? OTT 요금 및 정책 변경 정리","contents":"","link":"https://www.elle.co.kr/article/81126","retrieved":1696570806330},{"title":"제니부터 정국, 이효리까지! 올가을 귀 호강 예약 신보 소식.list","contents":"빛이 나는 솔로, 황금막내, 디바의 귀환?","link":"https://www.elle.co.kr/article/81125","retrieved":1696570806332},{"title":"최대 시청자 25만 명, 전설이 된 '나는 솔로' 16기 라방에서 나온 말들 (ft. 현커)","contents":"","link":"https://www.elle.co.kr/article/81116","retrieved":1696527629089}]}