{"title":"엘르 코리아 ─ 컬쳐 ─ 뮤직","url":"https://www.elle.co.kr/culture/music","favicon":"https://www.elle.co.kr/culture/favicon.ico","elements":[{"title":"연기-연예-가요대상급 관객석! 브루노 마스 내한 콘서트 관람 포착된 셀럽은?","contents":"","link":"https://www.elle.co.kr/article/78463","retrieved":1687196431597,"image":"https://image.jtbcplus.kr/data/contents/jam_photo/202306/19/8b70c0d0-7a52-4ffc-b6d7-d6d206d6dfce.jpg"},{"title":"텐션 업! 에너지 업! 시티포레스티벌 2023 비하인드","contents":"하루 종일 운동을 즐기며 에너지를 업시킬 수 있는 시티포레스티벌 2023의 기분 좋은 바이브","link":"https://www.elle.co.kr/article/78460","retrieved":1687196431598,"image":"https://image.jtbcplus.kr/data/contents/jam_photo/202306/19/8c8e2f20-c1cb-4949-aa34-e214d6aafabf.jpg"},{"title":"패션과 음악의 유기적 모멘트","contents":"런웨이와 무대 위에서 펼쳐지는 패션과 음악의 상관관계.","link":"https://www.elle.co.kr/article/78250","retrieved":1687110049653,"image":"https://image.jtbcplus.kr/data/contents/jam_photo/202306/19/a2eadd33-3011-4a40-898c-8ec12bb3ceaa.jpg"},{"title":"믿기지 않는 가격! 드디어 베일 벗은 애플의 야심작 ‘비전 프로’","contents":"헤드셋이 아닌 컴퓨터라고 불러주세요.","link":"https://www.elle.co.kr/article/78194","retrieved":1686159635168,"image":"https://image.jtbcplus.kr/data/contents/jam_photo/202306/07/d751c85b-8ab9-4b7f-bf56-443aee21d033.jpg"},{"title":"왜 해외 머글들이 뉴진스와 피프티피프티의 노래를 듣게 된 걸까?","contents":"스포티파이와 빌보드핫100 에서 써내려가고 있는 K팝 아티스트들의 놀라운 기록. K팝은 이제 '듣...","link":"https://www.elle.co.kr/article/78082","retrieved":1685727691557},{"title":"드디어 부활한 락 페스티벌과 혼네, 샘 스미스 내한까지! 2023 공연 라인업.list","contents":"","link":"https://www.elle.co.kr/article/78098","retrieved":1685727691563},{"title":"마크 론슨, 두아 리파, 그리고 피프티피프티?! '바비' OST까지 참여한 K-걸그룹의 기록.list","contents":"","link":"https://www.elle.co.kr/article/77968","retrieved":1685468494902},{"title":"온도, 습도, 분위기 모두 완벽! 초여름 밤의 낭만과 함께 한 #엘르스테이지2023","contents":"김윤아와 카더가든, 10cm가 꾸민 90분 간의 라이브 밴드 무대.","link":"https://www.elle.co.kr/article/77909","retrieved":1685122833455},{"title":"이토록 앙증맞은 레코더, 지금은 패션 브랜드로 거듭난 ‘이곳’에서 만들었다고?","contents":"아크네 스튜디오의 전신에서 출발한 스톡홀름 기반 오디오 브랜드, 틴에이지 엔지니어링.","link":"https://www.elle.co.kr/article/77654","retrieved":1684431647671},{"title":"베를린 필하모닉 사상 첫 동양인 여성 지휘자, 한국의 김은선","contents":"","link":"https://www.elle.co.kr/article/77457","retrieved":1683740604146},{"title":"구찌가 디자인한 바이닐의 가격은? 켄드릭 라마의 특별한 한정판 바이닐 비주얼.jpg","contents":"이건 꼭 소장해야 해.","link":"https://www.elle.co.kr/article/77444","retrieved":1683654091198},{"title":"선글라스 너머로, 나일 로저스의 눈빛","contents":"샤넬 아이웨어 캠페인을 위해 나일 로저스가 카메라 앞에 섰다. 비비안 로너, 신현지와 함께 눈...","link":"https://www.elle.co.kr/article/77430","retrieved":1683654091201},{"title":"90분의 라이브 밴드 '엘르 스테이지 콘서트' 김윤아, 10CM, 카더가든","contents":"&lt;엘르 스테이지 콘서트&gt;가 5월 20일, 노을이 지는 한강 노들섬에서 김윤아, 10CM, 카더가든의 ...","link":"https://www.elle.co.kr/article/77021","retrieved":1682444499031}]}