{"title":"엘르 코리아 ─ 뷰티","url":"https://www.elle.co.kr/beauty","favicon":"https://www.elle.co.kr/favicon.ico","elements":[{"title":"여름을 더 시원하게 날 수 있는 샤워 팁_선배's 어드바이스 #121","contents":"청량한 물보라에 휩싸이고픈 여름, 시원한 샤워용품들과 보디케어 팁.","link":"https://www.elle.co.kr/article/67162","retrieved":1655530864307,"image":"https://image.jtbcplus.kr/data/contents/jam_photo/202206/13/5fdd11ba-6b70-44c8-b926-eac274487c49.jpg"},{"title":"[특종] 잔망루피 최초 바캉스 화보.jpg","contents":"잔망루피와 슈퍼콜라겐 에센스 비오틴 한 잔 할래요? 잔망루피, 바이탈뷰티 뷰티 화보 공개!","link":"https://www.elle.co.kr/article/67128","retrieved":1655401615411,"image":"https://image.jtbcplus.kr/data/contents/jam_photo/202206/13/f0ce2186-1c4c-4b24-bfa3-cf7376154cdd.jpg"},{"title":"여름휴가를 떠난 스타들! 어떤 스윔웨어를 입었을까?","contents":"수영복 입으려고 여름 기다린 사람 손! 쇼핑 전 스타의 스윔웨어부터 스타일링까지 참고해보세요...","link":"https://www.elle.co.kr/article/67153","retrieved":1655358525229,"image":"https://image.jtbcplus.kr/data/contents/jam_photo/202206/13/f5828239-2fb5-49db-b511-4e7992fa997d.jpg"},{"title":"20년 경력의 프로 메이크업 아티스트가 추천하는 선크림 4","contents":"자외선과의 전쟁! 톱스타들의 메이크업 아티스트 홍현정이 추천하는 순하고, 눈 시림 없고, 안 ...","link":"https://www.elle.co.kr/article/67143","retrieved":1655358525234,"image":"https://image.jtbcplus.kr/data/contents/jam_photo/202206/11/065dbd09-d8f6-4d95-8757-97e5e514003d.jpg"},{"title":"정수리 탈모, 여름철 물미역 머리 타파! 두피 스크럽 3","contents":"에디터가 실제로 써 본 후기","link":"https://www.elle.co.kr/article/67094","retrieved":1655142472851,"image":"https://image.jtbcplus.kr/data/contents/jam_photo/202206/09/830d7daf-a478-4fd8-bc84-781fd42dc055.jpg"},{"title":"유이-여자친구 유주 몸매 비결, 폴댄스! 15분만 해도 런닝머신 1시간 뛴 효과?! #스타다이어트","contents":"많은 스타들이 사랑하는 건강 관리 운동, 폴댄스","link":"https://www.elle.co.kr/article/67076","retrieved":1655099121282,"image":"https://image.jtbcplus.kr/data/contents/jam_photo/202206/09/05f28fdf-4a88-459e-9504-cdde03b287ad.jpg"},{"title":"자유로운 남성을 위한 향수","contents":"블루 드 샤넬 새로운 광고 필름 공개!","link":"https://www.elle.co.kr/article/67001","retrieved":1655099121285,"image":"https://image.jtbcplus.kr/data/contents/jam_photo/202206/08/847333a0-87d8-4821-b674-03b5e983255c.jpg"},{"title":"글로시 파 vs 매트 파","contents":"당신의 선택은?","link":"https://www.elle.co.kr/article/66702","retrieved":1655055662046,"image":"https://image.jtbcplus.kr/data/contents/jam_photo/202206/07/d6615b7d-579c-4958-af65-efbf9e261c50.jpg"}]}