{"title":"엘르 코리아 ─ 스타","url":"https://www.elle.co.kr/star","favicon":"https://www.elle.co.kr/favicon.ico","elements":[{"title":"박신혜가 출산 후 3년 만에 돌아온다","contents":"","link":"https://www.elle.co.kr/article/83623","retrieved":1705081186170},{"title":"김대호가 밝힌 MBC 아나운서 시절 나경은 미담 (ft. 유재석 반응)","contents":"","link":"https://www.elle.co.kr/article/83610","retrieved":1705081186171},{"title":"허니제이 딸 정러브, 생후 8개월 만에 TV 데뷔?","contents":"","link":"https://www.elle.co.kr/article/83602","retrieved":1705081186172},{"title":"이장우, 우동집에 이어 순댓국집 오픈! 여자친구 조혜원의 방문 인증샷.jpg","contents":"","link":"https://www.elle.co.kr/article/83600","retrieved":1705038017138},{"title":"역주행 부담감에 극단적 체중 감량? 고충 토로했던 브브걸 근황 #스타다이어트","contents":"","link":"https://www.elle.co.kr/article/83599","retrieved":1704994784206},{"title":"눈빛에서 꿀 뚝뚝! 마이큐가 찍은 김나영 사진.jpg #럽스타그램","contents":"","link":"https://www.elle.co.kr/article/83585","retrieved":1704994784208},{"title":"신혜선X지창욱 로맨스의 향방은? '웰컴투 삼달리' 후반부 관전 포인트 #요즘드라마","contents":"","link":"https://www.elle.co.kr/article/83558","retrieved":1704951613524},{"title":"미국 골든글로브 남주상 탄 스티븐 연의 뭉클 수상 소감.txt","contents":"","link":"https://www.elle.co.kr/article/83557","retrieved":1704908369963}]}