{"title":"엘르 코리아 ─ 컬쳐 ─ 러브&라이프","url":"https://www.elle.co.kr/loveandlife","favicon":"https://www.elle.co.kr/favicon.ico","elements":[{"title":"스타들의 오프 더 레코드 (feat. 사복 패션)","contents":"쉬는 날 스타들은 뭐할까? 수수한 모습이 더 아름다운 스타들의 내추럴한 카메라 밖 모습을 모...","link":"https://www.elle.co.kr/article/79913","retrieved":1692380550784},{"title":"'위대한 이탈리아 비전: 파르네시나 컬렉션' 답이 아닌 질문인 예술을 만나다 #요즘전시","contents":"","link":"https://www.elle.co.kr/article/79904","retrieved":1692380550832},{"title":"언니 여기 어디예요? 장희령이 방문한 카페 3","contents":"신사동부터 한남동까지, 커피 러버들 마음 설레게 할 카페 리스트를 지금 확인해 보세요.","link":"https://www.elle.co.kr/article/79856","retrieved":1692380550834},{"title":"도심 속 안식처 같은 카페 2","contents":"분주한 일상을 뒤로한 채, 느린 호흡으로 마주한 여름날의 안식처.","link":"https://www.elle.co.kr/article/79798","retrieved":1692337323879},{"title":"취향 따라 즐겨봐! '1인 1빙' 가능한 경복궁 근처 빙수 맛집 2 #마실마실","contents":"더위를 잊게 할 형형색색의 빙수들.","link":"https://www.elle.co.kr/article/79850","retrieved":1692250937032},{"title":"여름날의 댕댕이들","contents":"수영부터 패들보드, 캠핑까지. 놀 줄 아는 강아지들의 시원한 여름 나기.","link":"https://www.elle.co.kr/article/79795","retrieved":1692250937035},{"title":"숲길 거닐며 힐링! 한여름밤 무더위 날릴 8월 야간 축제 3 #가볼만한곳","contents":"","link":"https://www.elle.co.kr/article/79845","retrieved":1692207703610},{"title":"옷잘알 셀럽들이 휴가를 즐기는 방법! 도시 ver.","contents":"도시 여행에 어울리는 스타일을 따로 있어요. 티파니, 슬기, 한소희 등 당장 따라 입고 싶은 ...","link":"https://www.elle.co.kr/article/79822","retrieved":1692034905809}]}