{"title":"엘르 코리아 ─ 뷰티","url":"https://www.elle.co.kr/beauty","favicon":"https://www.elle.co.kr/favicon.ico","elements":[{"title":"이렇게만 하면 꿀피부 보장? 손태영의 홈 케어 루틴 공개!","contents":"결점 없는 피부를 유지하기 위한 노력은 계속된다! 꼼꼼한 이중 세안부터 윤곽 관리까지, 손태영...","link":"https://www.elle.co.kr/article/81050","retrieved":1696527618659},{"title":"제대로 '입 터진' 순간들","contents":"하늘은 높고 말은 살찌는 풍요의 계절!","link":"https://www.elle.co.kr/article/81008","retrieved":1696484406085},{"title":"추석 음식 먹고 살찌기 전 저장! 윤은혜X한혜진X장영란의 '급찐급빠' 노하우 모음 #스타다이어트","contents":"","link":"https://www.elle.co.kr/article/81030","retrieved":1696484406094},{"title":"추석 연휴 시작 전 미리 저장 각! 한혜진의 2주 다이어트 Tip","contents":"건강하게 다이어트를 하고 싶다면 주목! 근육은 유지하고 체지방만 빼는 한혜진의 2주 다이어트.","link":"https://www.elle.co.kr/article/81028","retrieved":1696398016675},{"title":"우리나라의 웰비잉 순위는 세계 몇 위일까?","contents":"지금 전 세계는 웰비잉 딜레마! 룰루레몬의 2023 글로벌 웰비잉 리포트 읽기.","link":"https://www.elle.co.kr/article/80966","retrieved":1696354819065},{"title":"내 피부 장벽을 지켜줄 pH 농도는?_선배’s 어드바이스 #187","contents":"약산성, 미산성? 피부 건강과 직결된 pH! 간과하고 있었다면 주목.","link":"https://www.elle.co.kr/article/80890","retrieved":1696225207112},{"title":"열 살은 어려보이게! 한혜진표 동안 메이크업 Tip","contents":"입체적인 페이스 라인과 도톰한 애교살이 포인트. 메이크업만으로 어려 보일 수 있는 톱모델의 ...","link":"https://www.elle.co.kr/article/80848","retrieved":1696095635545},{"title":"23 F/W 아이 메이크업 트렌드","contents":"이번 시즌 반드시 숙지해야 할 아이 메이크업 트렌드 빅 4.","link":"https://www.elle.co.kr/article/80846","retrieved":1696052404245}]}