{"title":"엘르 코리아 ─ 패션","url":"https://www.elle.co.kr/fashion","favicon":"https://www.elle.co.kr/favicon_elle.ico?v=20190812","elements":[{"title":"샤넬이 창조한 코코 크러쉬의 세계","contents":"우아함의 본질을 담은 코코 크러쉬의 무한 변주.","link":"https://www.elle.co.kr/article/63506","retrieved":1643823730283,"image":"https://image.jtbcplus.kr/data/contents/jam_photo/202202/01/21169404-9276-423f-baec-f946de22472a.jpg"},{"title":"지금 가장 핫한 주얼리, 샤넬 코코 크러쉬","contents":"하나, 둘, 셋, 리드미컬한 리듬과 반복, 변형을 통해 완성한 코코 크러쉬의 변주.","link":"https://www.elle.co.kr/article/63485","retrieved":1643823730288,"image":"https://image.jtbcplus.kr/data/contents/jam_photo/202201/31/2c5e0958-fa13-4489-a922-5c73b11dfceb.jpg"},{"title":"거리에서 구조된 강아지 8 #사지마세요_입양하세요 #LoveMIX","contents":"거리에서 구조된 사랑스러운 강아지들을 위해 세상에서 가장 ‘쿨’한 켄넬이 된 오버사이즈 백 ...","link":"https://www.elle.co.kr/article/63476","retrieved":1643823730299,"image":"https://image.jtbcplus.kr/data/contents/jam_photo/202201/30/8c9edf56-e474-4c6a-a12e-99ee29bcb6a3.jpg"},{"title":"10만 원 이하, 센스있는 설 선물","contents":"설 선물 고민 중이라면 주목! 10만 원 이하로 살 수 있는 감각적이고 실용적인 설 선물 리...","link":"https://www.elle.co.kr/article/63471","retrieved":1643823730320,"image":"https://image.jtbcplus.kr/data/contents/jam_photo/202201/29/5a95bac1-3ce5-46bc-9e9e-03e41490d049.jpg"},{"title":"작심삼일 금지! 운동할 맛 나는 스타들의 운동복","contents":"골프부터 필라테스, 테니스, 스키, 발레까지! 운동에 진심인 스타들의 운동복 스타일은 바로 ...","link":"https://www.elle.co.kr/article/63468","retrieved":1643823730320,"image":"https://image.jtbcplus.kr/data/contents/jam_photo/202201/29/8e4407a6-41a3-439f-9a42-57e70449a400.jpg"},{"title":"'첫 독립'에 이렇게? 웰컴 투 다라 하우스 #랜선집들이","contents":"다라 하우스에서 무채색 아이템은 금지! 알록달록한 컬러가 기분 좋게 만드는 그녀의 집에 놀러...","link":"https://www.elle.co.kr/article/63407","retrieved":1643823730321,"image":"https://image.jtbcplus.kr/data/contents/jam_photo/202201/28/f4348884-1982-495d-84cb-107143d12e70.jpg"},{"title":"K토종 댕댕이, 지금 만나러 갑니다 #LoveMIX","contents":"진돗개와 동경이와 삽살이. K토종 댕댕이들을 지금 만나러 갑니다.","link":"https://www.elle.co.kr/article/63404","retrieved":1643823730321,"image":"https://image.jtbcplus.kr/data/contents/jam_photo/202201/28/fe2136c2-b90c-4d1d-9fea-614da5b4f3fc.jpg"},{"title":"준비물은 오직 머리끈! 어렵지 않은 브레이드 헤어 룩","contents":"고무줄 하나로 ‘힙’해지는 방법! 브레이드 헤어의 매력에 빠진 셀러브리티들을 모아봤어요.","link":"https://www.elle.co.kr/article/63361","retrieved":1643521162899,"image":"https://image.jtbcplus.kr/data/contents/jam_photo/202201/27/8d69db6d-59a9-4f2d-86b8-2f9161a7d837.jpg"}]}