{"title":"엘르 코리아 ─ 패션","url":"https://www.elle.co.kr/fashion","favicon":"https://www.elle.co.kr/favicon.ico","elements":[{"title":"로에베가 전하는 조형적인 아름다움","contents":"강인하면서도 유연하게.","link":"https://www.elle.co.kr/article/84687","retrieved":1709962782318},{"title":"동아시아 무드로 만난 패션","contents":"격렬하면서도  고요한 움직임으로 담아낸 뉴 시즌의 정제된 키 룩 15.","link":"https://www.elle.co.kr/article/84600","retrieved":1709919555992},{"title":"요즘 스커트 스타일링은 이렇게! #벌룬스커트","contents":"스커트 어울리는 계절을 위해 추천하는 벌룬 스커트! 풍성하고 통통할수록 예뻐요.","link":"https://www.elle.co.kr/article/84684","retrieved":1709919555999},{"title":"루이비통의 그 시계","contents":"주목해야할 루이비통의 성장형 시계","link":"https://www.elle.co.kr/article/84657","retrieved":1709833169386},{"title":"샤넬 프리미에르의 새로운 얼굴","contents":"시대를 초월한 샤넬 프리미에르 워치의 뮤즈, 제니와 함께한 2024 캠페인","link":"https://www.elle.co.kr/article/84665","retrieved":1709833169392},{"title":"탐나는 스타일링 공식! 팬츠 더하기 스커트 5","contents":"올봄 주목해야 할 레이어드 트렌드를 짚어드려요! 팬츠 위에 스커트를 더하는 레이어드 기술로 ...","link":"https://www.elle.co.kr/article/84655","retrieved":1709789968233},{"title":"‘사복 천재’ 스타들의 트렌치코트 패션 5","contents":"김나영, 정유미, 차정원 등 트렌치코트 입고 봄을 맞이한 스타들.","link":"https://www.elle.co.kr/article/84627","retrieved":1709789968236},{"title":"알렉산더 맥퀸의 새 시대","contents":"션 맥기르가 알렉산더 맥퀸에 새로운 바람을 일으켰다.","link":"https://www.elle.co.kr/article/84619","retrieved":1709789968237}]}