{"title":"엘르 코리아 ─ 패션","url":"https://www.elle.co.kr/fashion","favicon":"https://www.elle.co.kr/favicon.ico","elements":[{"title":"연말 선물 고민이라면? 10만원대 이하 선물 Best 8 (ft.레이디제인)","contents":"여기저기 선물할 곳이 많아지는 연말, 레이디제인이 꼽은 가성비와 가심비를 모두 잡은 선물 리...","link":"https://www.elle.co.kr/article/83124","retrieved":1703223560088},{"title":"크리스마스를 위한 레드 스웨터 #쇼핑리스트","contents":"드레스코드는 레드! 크리스마스 분위기를 제대로 즐기기 위한 레드 스웨터 일곱 가지.","link":"https://www.elle.co.kr/article/83100","retrieved":1703223560090},{"title":"테이블 위 메리 크리스마스!","contents":"테이블 위에서 펼쳐지는 따스하고 감각적인 크리스마스 기프트.","link":"https://www.elle.co.kr/article/83099","retrieved":1703093966466},{"title":"진짜보다 아름다운 페이크 퍼 코트","contents":"진짜보다 아름다운 페이크 퍼 코트더 풍성하고 과감하게.","link":"https://www.elle.co.kr/article/83056","retrieved":1703093966467},{"title":"이 신인 모델을 주목하세요!","contents":"","link":"https://www.elle.co.kr/article/83055","retrieved":1703093966469},{"title":"스웨이드 슈즈의 두 가지 면모","contents":"클래식하고 캐주얼하게.","link":"https://www.elle.co.kr/article/83049","retrieved":1703050757610},{"title":"지수부터 켄달 제너까지, 멋쟁이는 겨울에도 가죽을 입는다!","contents":"옷 잘 입는 스타들의 5인 5색 레더 패션 모음.zip","link":"https://www.elle.co.kr/article/83048","retrieved":1702964370920},{"title":"꿈꾸는 크리스마스 트리","contents":"크리스마스트리 위에 반짝이는 오너먼트처럼 밋밋한 룩도 특별하게 업그레이드해 줄 백들이 쏟아졌...","link":"https://www.elle.co.kr/article/83046","retrieved":1702921170326}]}