{"title":"엘르 코리아 ─ 뷰티","url":"https://www.elle.co.kr/beauty","favicon":"https://www.elle.co.kr/favicon.ico","elements":[{"title":"드림 스킨, 세럼 한 방울로 완성할 수 있다","contents":"어떤 피부 고민도 바로 개선하는 원 드롭 올라운더, 아벤느 시칼파트+.","link":"https://www.elle.co.kr/article/84825","retrieved":1711085957453},{"title":"뜯지 마세요, 립밤에 양보하세요_선배’s 어드바이스 #212","contents":"연중 가장 건조한 시기, 입술 각질 부자에게 최강 보습을 선물할 립밤 모음.zip","link":"https://www.elle.co.kr/article/84871","retrieved":1711085957455},{"title":"멋을 아는 언니, 엄정화의 뷰티 아이템 9","contents":"자기 전에 뿌리는 향수부터 도톰한 입술을 만들어 주는 플럼핑 립스틱까지, 엄정화의 취향이 느...","link":"https://www.elle.co.kr/article/84864","retrieved":1711042798051},{"title":"핸드크림 쇼핑","contents":"봄맞이 핸드크림 쇼핑 위시리스트!","link":"https://www.elle.co.kr/article/84796","retrieved":1710999583415},{"title":"오마이걸 유아가 통통 볼살 쏙 뺀 비결은? #스타다이어트","contents":"","link":"https://www.elle.co.kr/article/84831","retrieved":1710869972321},{"title":"뉴진스 민지가 선택한, 어린 생기와 활력을 선사하는 세럼","contents":"혹독한 환경 속에서 기어코 꽃을 피우는 레드 까멜리아처럼, 민지의 얼굴에 강인한 생명력이 움...","link":"https://www.elle.co.kr/article/84806","retrieved":1710783574390},{"title":"야, 너두 오버립 할 수 있어 (feat.로즈 립 펜슬)","contents":"정교한 풀 립(Full Lip)부터 매력적인 오버립까지 이것만 있으면 '쌉가능!' 로즈 누드 톤의 립...","link":"https://www.elle.co.kr/article/84815","retrieved":1710740365338},{"title":"셀린느 립스틱, 발색 여기서 보세요","contents":"셀린느의 24 아크 드 트리옹프 컬렉션 영상을 공개합니다.","link":"https://www.elle.co.kr/article/84814","retrieved":1710740365339}]}