{"title":"엘르 코리아 ─ 패션","url":"https://www.elle.co.kr/fashion","favicon":"https://www.elle.co.kr/favicon.ico","elements":[{"title":"사물(사람과 물건) 인터뷰 #8 스타일리스트 김영진","contents":"고작 900원? BTS 스타일리스트 김영진이 애정하는 물건.","link":"https://www.elle.co.kr/article/81377","retrieved":1697650837300,"image":"https://image.jtbcplus.kr/data/contents/ham_photo/202310/16/26c61593-91be-44b9-9c27-e85906c6e5aa.jpg"},{"title":"알 쓸 신 작","contents":"알아두면 쓸데 있는 신비한 작품 속 시계와 주얼리들.","link":"https://www.elle.co.kr/article/81311","retrieved":1697607629867,"image":"https://image.jtbcplus.kr/data/contents/ham_photo/202310/16/0113d587-48da-49bb-9b06-5dda587e6b59.jpg"},{"title":"스타들이 데님을 즐기는 방법 #청청패션","contents":"대충 입어도 멋있다! 로제부터 전소미까지 스타일리시한 데님 패션의 모든 것.","link":"https://www.elle.co.kr/article/81367","retrieved":1697607629869,"image":"https://image.jtbcplus.kr/data/contents/ham_photo/202310/15/aa7baf81-315b-4ccb-9be2-27b6a85ccb33.jpg"},{"title":"아트로 진화한 가방","contents":"","link":"https://www.elle.co.kr/article/81366","retrieved":1697521191146,"image":"https://image.jtbcplus.kr/data/contents/ham_photo/202310/15/da6e5358-9a62-42b4-93fc-6dd527929124.jpg"},{"title":"진리의 화이트 다이아몬드","contents":"어둠 속에서 진가를 드러내는 화이트 다이아몬드.","link":"https://www.elle.co.kr/article/81341","retrieved":1697478030454,"image":"https://image.jtbcplus.kr/data/contents/ham_photo/202310/14/87d40fc1-f7f3-440b-ab26-8e8e6a2f00df.jpg"},{"title":"르세라핌과 루이 비통의 반가운 조우","contents":"","link":"https://www.elle.co.kr/article/81360","retrieved":1697434796590,"image":"https://image.jtbcplus.kr/data/contents/ham_photo/202310/14/1fa9574f-2bad-41eb-a098-d7da3448b26b.jpg"},{"title":"올가을 스타일 치트키! 스타킹 활용하는 법","contents":"멋있는 언니들은 스타킹을 신지!","link":"https://www.elle.co.kr/article/81356","retrieved":1697434796591,"image":"https://image.jtbcplus.kr/data/contents/ham_photo/202310/14/45b1bcfe-a8a9-4905-98a8-132bac41b3be.jpg"},{"title":"보기 좋은 '빗'이 '빗기도' 좋다","contents":"갖고 싶어, 그 빗!","link":"https://www.elle.co.kr/article/81296","retrieved":1697348389717,"image":"https://image.jtbcplus.kr/data/contents/ham_photo/202310/14/ad95ece6-79d1-4431-a4e4-c1ed4403c5cf.jpg"}]}