{"title":"엘르 코리아 ─ 패션","url":"https://www.elle.co.kr/fashion","favicon":"https://www.elle.co.kr/favicon.ico","elements":[{"title":"#내돈내산 죽은 스케치도 살려주는 1천5백원 짜리 붓펜?","contents":"#사람과물건 인터뷰 011 굼허 디렉터 허금연","link":"https://www.elle.co.kr/article/83964","retrieved":1706679557460},{"title":"해피 뉴 헤어! 새해 맞이 헤어 변신한 스타 5","contents":"아이유와 한예슬, 아이브의 가을까지! 확실한 이미지 변신을 원한다면 헤어 스타일을 바꿔보세요.","link":"https://www.elle.co.kr/article/83959","retrieved":1706679557461},{"title":"손끝까지 반짝반짝! 스타들의 네일 아트 5","contents":"네일 숍 가기 전 참고하세요.","link":"https://www.elle.co.kr/article/83954","retrieved":1706636374909},{"title":"헤일리 비버의 손바닥만 한 미니드레스 열전.","contents":"아슬아슬하게, 아찔하게.","link":"https://www.elle.co.kr/article/83921","retrieved":1706636374917},{"title":"르세라핌 'EASY' 트레일러 미공개 스틸 컷","contents":"\"세상이 우리에게만 쉬운 것 같니? 내가 진짜 비밀을 알려줄게\" 르세라핌(LE SSERAFIM)이 미니...","link":"https://www.elle.co.kr/article/83944","retrieved":1706593171563},{"title":"GD도 반했다! CES2024에서 발견한 흥미로운 AI 집템 3","contents":"","link":"https://www.elle.co.kr/article/83940","retrieved":1706506776683},{"title":"파리에 도착한 단추","contents":"그랑 팔레에서 공개된 샤넬 24 SS 쿠튀르 컬렉션.","link":"https://www.elle.co.kr/article/83924","retrieved":1706506776688},{"title":"날카롭고 예리한 시선으로, 메탈 프레임 안경","contents":"안경 선배 처럼.","link":"https://www.elle.co.kr/article/83918","retrieved":1706420358491}]}