{"title":"엘르 코리아 ─ 뷰티","url":"https://www.elle.co.kr/beauty","favicon":"https://www.elle.co.kr/favicon.ico","elements":[{"title":"전소미가 슬림 탄탄 체형 완성에 적극 추천한 운동법은? #스타다이어트","contents":"","link":"https://www.elle.co.kr/article/79796","retrieved":1692034824570,"image":"https://image.jtbcplus.kr/data/contents/jam_photo/202308/09/c93da293-dec6-467b-b394-e21de9552eea.jpg"},{"title":"유리처럼 맑고 투명하게. 글래스를 기억해!","contents":"패션에서 뷰티까지, 키워드는 글래스(glass).","link":"https://www.elle.co.kr/article/79777","retrieved":1691948426341,"image":"https://image.jtbcplus.kr/data/contents/jam_photo/202308/09/3309bb02-f234-4eb5-b1da-e07f3805d293.jpg"},{"title":"엄정화가 알려주는 데일리 메이크업 튜토리얼","contents":"매일 리즈 갱신하는 엄정화의 메이크업 팁이 궁금하다면 주목! 관능적이고 섹시미 넘치는 데일리...","link":"https://www.elle.co.kr/article/79774","retrieved":1691862031697,"image":"https://image.jtbcplus.kr/data/contents/jam_photo/202308/09/b94966da-ca55-4d18-a475-84d8211d96e4.jpg"},{"title":"피부 온도 31도를 사수하라! 진정 & 보습 끝판왕 스킨케어 TIP 4_선배’s 어드바이스 #180","contents":"기록적 폭염에 피부는 열 노화 중? 건강한 피부 온도 지키는 비법 대공개!","link":"https://www.elle.co.kr/article/79731","retrieved":1691689203242,"image":"https://image.jtbcplus.kr/data/contents/jam_photo/202308/08/d895d189-6d31-4899-a23c-42ef0c4be271.jpg"},{"title":"일상에 하트 더하기! 스타의 하트 모티프 패션 6","contents":"하트 덕후 모여라~ 가방부터 티셔츠, 얼굴에 붙인 포인트 파츠까지 하트로 가득한 패션을 소개합...","link":"https://www.elle.co.kr/article/79720","retrieved":1691602821930,"image":"https://image.jtbcplus.kr/data/contents/jam_photo/202308/06/a9abff36-3269-45d5-a606-b613527f1be3.jpg"},{"title":"'워터밤 여신' 권은비! 건강미의 핵심 비결은 바로 이것? #스타다이어트","contents":"","link":"https://www.elle.co.kr/article/79678","retrieved":1691602821931,"image":"https://image.jtbcplus.kr/data/contents/jam_photo/202308/03/1b8e40ed-5253-40d8-bac1-4e286ab0596d.jpg"},{"title":"여름 메이크업의 킥! #주근깨메이크업","contents":"열심히 가릴 필요 없습니다. 일부러 그려 넣는 주근깨 메이크업이 트렌드니까요!","link":"https://www.elle.co.kr/article/79662","retrieved":1691559633718,"image":"https://image.jtbcplus.kr/data/contents/jam_photo/202308/03/73a56941-388a-40a3-97d1-3afec5f144f0.jpg"},{"title":"강민경이 '입금 다이어트'할 때 반드시 챙겨 먹는 음식은? #스타다이어트","contents":"","link":"https://www.elle.co.kr/article/79658","retrieved":1691559633719,"image":"https://image.jtbcplus.kr/data/contents/jam_photo/202308/02/df4709f2-7e1d-4ed6-b724-e7bfb647db55.jpg"}]}