{"title":"엘르 코리아 ─ 컬쳐 ─ 러브&라이프","url":"https://www.elle.co.kr/loveandlife","favicon":"https://www.elle.co.kr/favicon.ico","elements":[{"title":"샛노란 유채꽃에 벚꽃, 푸른 바다까지? 보기만 해도 힐링되는 제주 명소 3 #가볼만한곳","contents":"","link":"https://www.elle.co.kr/article/76384","retrieved":1680630160558,"image":"https://image.jtbcplus.kr/data/contents/jam_photo/202303/31/bb304409-2193-4d69-8255-c8b63568812c.jpg"},{"title":"맛잘알 조현아 따라 맛집 투어 3","contents":"미쉐린 가이드에 등극한 순대 오마카세부터 지리산 정기를 가득 품은 흑돼지 맛집까지, 먹킷리스...","link":"https://www.elle.co.kr/article/76368","retrieved":1680586906958,"image":"https://image.jtbcplus.kr/data/contents/jam_photo/202303/31/c377dda7-b221-47a9-a9c7-29f4f73f30f2.jpg"},{"title":"봄날의 한옥 스테이","contents":"놀랍도록 새로운 얼굴로 탄생한 한옥 스테이. 시간이 천천히 흐르는 이곳에 아름드리 봄이 온다...","link":"https://www.elle.co.kr/article/76344","retrieved":1680543684928,"image":"https://image.jtbcplus.kr/data/contents/jam_photo/202304/02/fdcf2519-99a2-4b3b-8861-0cdae735a4c9.jpg"},{"title":"에르메스가 48년생 그 작가를 주목한 이유?","contents":"아틀리에 에르메스가 후원하는 &lt;크리스티앙 본느프와 : 토끼의 질주&gt; 전시를 소개합니다.","link":"https://www.elle.co.kr/article/76241","retrieved":1680327658857,"image":"https://image.jtbcplus.kr/data/contents/jam_photo/202303/28/f6c4dca8-8bc5-4ae6-86df-67c3aa42ea3c.jpg"},{"title":"로맨틱 그 자체! 반짝이는 야경을 만끽할 수 있는 전국 빛 축제 3 #가볼만한곳","contents":"","link":"https://www.elle.co.kr/article/76232","retrieved":1680284521484,"image":"https://image.jtbcplus.kr/data/contents/jam_photo/202303/28/177baeda-c624-4937-b577-9d43797f5957.jpg"},{"title":"치즈 농장과 서울의 작은 유럽으로 떠나는 봄나들이! 익선동-삼청동-상수동 #신상맛집 3","contents":"","link":"https://www.elle.co.kr/article/76208","retrieved":1680284521486,"image":"https://image.jtbcplus.kr/data/contents/jam_photo/202303/28/ad154bb5-4ae6-40bc-ad68-3ec55ab891a0.jpg"},{"title":"채소와 함께한 시간","contents":"&lt;채소의 계절&gt;을 펼쳤다. 요리사 재인이 채소와 함께 살아낸 열두 달의 기록을.","link":"https://www.elle.co.kr/article/76194","retrieved":1680241303825,"image":"https://image.jtbcplus.kr/data/contents/jam_photo/202303/27/a69502fc-7dfc-441d-978a-708346b1faf0.jpg"},{"title":"주우재가 단골 인증한 가로수길 핫플은 어디?","contents":"에스프레소 바부터 쇼핑 스폿까지, 가로수길을 제대로 즐기고 싶다면 주목하세요.","link":"https://www.elle.co.kr/article/76140","retrieved":1680198343768,"image":"https://image.jtbcplus.kr/data/contents/jam_photo/202303/26/f80669c7-dcd3-4b13-a0d4-b0a646974fbd.jpg"}]}