{"title":"엘르 코리아 ─ 컬쳐 ─ 러브&라이프","url":"https://www.elle.co.kr/loveandlife","favicon":"https://www.elle.co.kr/favicon.ico","elements":[{"title":"올드머니 느낌 물씬! 뉴트럴톤 하우스","contents":"카다시안 절친 사이먼 허크가 공개한 그의 신혼집.","link":"https://www.elle.co.kr/article/81170","retrieved":1697089302672,"image":"https://image.jtbcplus.kr/data/contents/ham_photo/202310/08/00de2f62-744e-4884-8bda-10b30f4de6f8.jpg"},{"title":"일본에서 꼭 사와야 할 파우치템 7 #도쿄핫플","contents":"K-뷰티가 전 세계를 장악했다지만 일본에는 여전히 쓸만한 뷰티 아이템이 즐비합니다. 뷰티 인사...","link":"https://www.elle.co.kr/article/81184","retrieved":1697002903263,"image":"https://image.jtbcplus.kr/data/contents/ham_photo/202310/10/26e0916e-c933-4111-bb08-7dd7fdb59aa4.jpg"},{"title":"울긋불긋 가을 머금은 창밖이 있는 단풍 뷰 카페 in 종로 #마실마실","contents":"그윽해진 서울의 풍경을 감상할 수 있는 카페 두 곳.","link":"https://www.elle.co.kr/article/81181","retrieved":1696959670139,"image":"https://image.jtbcplus.kr/data/contents/ham_photo/202310/06/c6abf216-5a8e-4a15-b9d5-8fb7a39895b6.jpg"},{"title":"아직 늦지 않았다! 2023 여의도 불꽃축제, 체크해야 할 불꽃 명당 3 #가볼만한곳","contents":"","link":"https://www.elle.co.kr/article/81178","retrieved":1696959670142,"image":"https://image.jtbcplus.kr/data/contents/ham_photo/202310/06/162bca78-60c5-4f5e-b8d2-6405e0f58541.jpg"},{"title":"로컬 맛집부터 쇼핑까지! 윤승아 따라 연희동 한 바퀴.list","contents":"이번 주말, 느긋하게 쇼핑하면서 커피 한 잔의 여유를 즐기고 싶다면 윤승아의 발자취를 따라 ...","link":"https://www.elle.co.kr/article/81167","retrieved":1696743676870,"image":"https://image.jtbcplus.kr/data/contents/ham_photo/202310/06/a5a2c129-2119-4e70-b7bc-2f0b811432ab.jpg"},{"title":"전설의 주윤발, 판빙빙이 한국에? 제28회 부산국제영화제 레드카펫.jpg","contents":"7년 만에 한국을 찾는 주인공은?","link":"https://www.elle.co.kr/article/81111","retrieved":1696700467418,"image":"https://image.jtbcplus.kr/data/contents/ham_photo/202310/05/cdfc4cb0-05de-4968-b431-582fa748b4db.jpg"},{"title":"추석에 살쪘다면 주목! 남은 명절 음식으로 만드는 다이어트 레시피 3","contents":"","link":"https://www.elle.co.kr/article/81062","retrieved":1696614059709,"image":"https://image.jtbcplus.kr/data/contents/ham_photo/202310/04/0522e753-2207-469b-896e-f73c64980988.jpg"},{"title":"가을이 성큼! 제철을 맞은 무화과 디저트 맛집 3","contents":"유난히 짧아 더 아쉬운 무화과 철을 제대로 즐기는 법. 가을 한정 무화과 디저트 맛집에 방문...","link":"https://www.elle.co.kr/article/81039","retrieved":1696614059710,"image":"https://image.jtbcplus.kr/data/contents/ham_photo/202310/01/4370ca8c-50e4-4536-8f56-a72caaa28c05.jpg"}]}