{"title":"엘르 코리아 ─ 뷰티","url":"https://www.elle.co.kr/beauty","favicon":"https://www.elle.co.kr/favicon.ico","elements":[{"title":"논픽션과 딥티크의 여름","contents":"논픽션과 딥티크에서 여름을 맞아 새로운 향 컬렉션을 선보인다.","link":"https://www.elle.co.kr/article/78586","retrieved":1689097239843,"image":"https://image.jtbcplus.kr/data/contents/jam_photo/202307/06/b102901f-fd19-4228-9e9b-3e2026f69338.jpg"},{"title":"'1인 1닭' 가능? 대식가 문가영의 체형 유지 비결! #스타다이어트","contents":"","link":"https://www.elle.co.kr/article/78957","retrieved":1689097239846,"image":"https://image.jtbcplus.kr/data/contents/jam_photo/202307/05/7698f7d7-3ee0-4bb1-b86e-65f18e960e5e.jpg"},{"title":"윤승아가 N년째 애용하는 공병템 5","contents":"10년 넘게 윤승아의 화장대 위에 꾸준히 자리하고 있는 아이템은 무엇? 매일 사용하는 보습 크...","link":"https://www.elle.co.kr/article/78931","retrieved":1689054026225,"image":"https://image.jtbcplus.kr/data/contents/jam_photo/202307/05/16183900-b99b-4b33-976f-087124b2ac02.jpg"},{"title":"폭염특보에 지친 피부와 모발에는? 얼음 샤워한 듯 시원한 쿨링 테라피 TIP 3_선배’s 어드바이스 #175","contents":"머리부터 발끝까지 번아웃 위기에 빠진 내 몸을 구하라!","link":"https://www.elle.co.kr/article/78893","retrieved":1688967655422,"image":"https://image.jtbcplus.kr/data/contents/jam_photo/202307/03/2b2e712b-5b2a-4df8-a710-f518f2b837cf.jpg"},{"title":"이거 뿌리면 사람들이 다 물어볼걸? 강민경의 상황별 추천 향수 9","contents":"강민경이 추천하고 이해리가 보증하는 향수 아홉 가지! 그날의 기분에 따라 매치해 보세요~","link":"https://www.elle.co.kr/article/78857","retrieved":1688622182195,"image":"https://image.jtbcplus.kr/data/contents/jam_photo/202307/10/08f55f9d-0382-45dd-965d-b8e9e82191dc.jpg"},{"title":"제니와 송혜교의 절친, 톱 모델 신현지가 48kg 유지 위해 아침마다 하는 운동은? #스타다이어트","contents":"","link":"https://www.elle.co.kr/article/78806","retrieved":1688578868681,"image":"https://image.jtbcplus.kr/data/contents/jam_photo/202306/29/743b0e88-6870-45b7-9a88-27940dd3d4ac.jpg"},{"title":"줄리엔강X제이제이! '피지컬 커플'의 운동 데이트 루틴 #스타다이어트","contents":"","link":"https://www.elle.co.kr/article/78762","retrieved":1688578868683,"image":"https://image.jtbcplus.kr/data/contents/jam_photo/202306/28/45e5fb67-a360-479e-ba81-00bda0f21fc8.jpg"},{"title":"습하고 끈적한 장마철, 하루 종일 보송한 무적의 베이스 메이크업 TIP 5_선배’s 어드바이스 #174","contents":"절대 무너지지 않는 베이스를 완성시켜줄 아이템, 똑똑하게 바르는 법은?","link":"https://www.elle.co.kr/article/78681","retrieved":1688578868684,"image":"https://image.jtbcplus.kr/data/contents/jam_photo/202306/27/9e09f650-d2de-4c31-b747-f3d637f3944f.jpg"}]}