{"title":"엘르 코리아 ─ 스타","url":"https://www.elle.co.kr/star","favicon":"https://www.elle.co.kr/favicon.ico","elements":[{"title":"‘피크타임’을 만난 TOP6가 새로운 출발선 위에 섰다 #2","contents":"한결, 혜성, 희재, D1, 빛새온, 문종업. 막 ‘피크타임’을 올라선 이들이 기어코 스포트라이트...","link":"https://www.elle.co.kr/article/76658","retrieved":1681623591826,"image":"https://image.jtbcplus.kr/data/contents/jam_photo/202304/13/3fb98912-8866-4cde-8467-e641e9ef21fe.jpg"},{"title":"‘피크타임’을 만난 TOP6가 새로운 출발선 위에 섰다 #1","contents":"한결, 혜성, 희재, D1, 빛새온, 문종업. 막 ‘피크타임’에 올라선 이들이 기어코 스포트라이트...","link":"https://www.elle.co.kr/article/76656","retrieved":1681537246457,"image":"https://image.jtbcplus.kr/data/contents/jam_photo/202304/14/72679389-96e8-4dce-8e06-d9ea6ae8f9e8.jpg"},{"title":"'너목들'로 만난 이종석X이보영! 벌써 10주년이라는데?","contents":"","link":"https://www.elle.co.kr/article/76663","retrieved":1681537246458,"image":"https://image.jtbcplus.kr/data/contents/jam_photo/202304/13/233de2a7-9324-404a-9d48-606c0bb9d6ca.jpg"},{"title":"결혼 후 첫 근황 전한 '하시3' 박지현! 자기관리에서 가장 강조한 것은? #스타다이어트","contents":"","link":"https://www.elle.co.kr/article/76659","retrieved":1681494028451,"image":"https://image.jtbcplus.kr/data/contents/jam_photo/202304/13/444f8c87-e52d-42b8-a0d8-765f0c2135cc.jpg"},{"title":"윤성빈, 서준맘과 운동하고 10cm, 카더가든, 김윤아 공연을 즐기는 웰니스 페스티벌이 있다고?","contents":"시티 포레스티벌 2023의 티켓 판매는 오늘부터.","link":"https://www.elle.co.kr/article/76654","retrieved":1681494028465,"image":"https://image.jtbcplus.kr/data/contents/jam_photo/202304/13/7e7edee0-b469-4c04-98b2-bfe262c1b038.jpg"},{"title":"크롭트 톱 입어볼까? 옷잘알 셀럽들의 스타일링 노하우 6","contents":"데일리 룩부터 격식을 갖춘 자리까지 활용 가능! 크롭트 톱, 어렵지 않아요.","link":"https://www.elle.co.kr/article/76644","retrieved":1681407619632,"image":"https://image.jtbcplus.kr/data/contents/jam_photo/202304/13/1b202eea-96ed-4ae8-8369-5dea55ded828.jpg"},{"title":"'더 마블스' 캡틴 마블 남편 된 박서준! 단 1초 만에 카리스마 입증한 비주얼.avi","contents":"영화 '드림'에선 청춘 캐릭터로 활약 예고!","link":"https://www.elle.co.kr/article/76639","retrieved":1681407619633,"image":"https://image.jtbcplus.kr/data/contents/jam_photo/202304/12/b51bdd92-24ed-4853-a97c-71505c7362a7.jpg"},{"title":"철저한 자기관리로 롱런하는 엄정화! 운동하면서 '이것'을 가장 강조했다는데? #스타다이어트","contents":"","link":"https://www.elle.co.kr/article/76636","retrieved":1681407619644,"image":"https://image.jtbcplus.kr/data/contents/jam_photo/202304/12/bd4e7a08-fc0b-4fbe-bdd5-c48fe2a2ed2b.jpg"}]}