{"title":"엘르 코리아 ─ 컬쳐 ─ 아트&디자인","url":"https://www.elle.co.kr/culture/artanddesign","favicon":"https://www.elle.co.kr/culture/favicon.ico","elements":[{"title":"박서보, 한 줄 이라도 더 긋고 싶은 아흔살 화백이 폐암 판정을 두고 한 다짐","contents":"폐암 3기 판정을 받고 올린 박서보 화백의 심경. \"전화하지 마시라, 그럼에도 말을 전하고 싶다...","link":"https://www.elle.co.kr/article/75304","retrieved":1677174127943,"image":"https://image.jtbcplus.kr/data/contents/jam_photo/202302/23/488084c3-b3d0-4365-97c2-61bc20fde3ff.jpg"},{"title":"아티스틱 스페이스","contents":"엘르 데코가 주목한 예술적인 공간 4.","link":"https://www.elle.co.kr/article/73000","retrieved":1677044514397,"image":"https://image.jtbcplus.kr/data/contents/jam_photo/202302/26/7985be61-77bf-4634-9899-df54fecfe546.jpg"},{"title":"한국의 근대 건축물 ⑤ 정동 1번지, 신아기념관","contents":"정동 1번지를 지켜온 신아기념관의 옛 애칭은 '졸리 하우스', '즐거운 집'이었다.","link":"https://www.elle.co.kr/article/72993","retrieved":1677044514398,"image":"https://image.jtbcplus.kr/data/contents/jam_photo/202302/20/e94cbfbb-b10e-4484-a9bf-54aa45e8a6df.jpg"},{"title":"홈 오브제 퍼레이드 ②","contents":"에르메스 2022 홈 컬렉션은 밝은 에너지를 담뿍 담았다. 상상을 초월하는 극강의 아름다움. 홈 ...","link":"https://www.elle.co.kr/article/75117","retrieved":1677044514398,"image":"https://image.jtbcplus.kr/data/contents/jam_photo/202302/20/cfa319cc-0a0b-4111-af99-73c0f7409a69.jpg"},{"title":"생트로페로 떠난 모험, 갤러리스트 아르멜 소예르가 꿈꾼 공간","contents":"10년 전 파리에 자신의 첫 갤러리를 오픈한 아르멜 소예르는 어느 날 프랑스 남부 생트로페로 ...","link":"https://www.elle.co.kr/article/72992","retrieved":1677044514398},{"title":"컬러풀 소파! 화이트 & 베이지","contents":"새하얗게 빛나는 휴식의 정점.","link":"https://www.elle.co.kr/article/72990","retrieved":1677044514400},{"title":"공간의 씬 스틸러들 ③ 아파트먼트풀","contents":"‘아파트먼트풀’은 경험을 채우며 진정한 취향과 마주할 수 있는 공간이다.","link":"https://www.elle.co.kr/article/72988","retrieved":1677044514401},{"title":"새로운 차원의 영감! 디지털 방식으로 창조한 집과 세계","contents":"렌더링 디자인은 이제 다른 차원의 영감을 선사하는 원천이 되고 있다. 재해석한 70년대 색채와...","link":"https://www.elle.co.kr/article/72987","retrieved":1677044514402},{"title":"슬기가 다녀간 ‘핫’한 전시는 어디?","contents":"예술적 감각이 뛰어난 슬기가 찾은 전시 두 곳을 확인하고 느낌 있는 인증샷을 남겨 보세요.","link":"https://www.elle.co.kr/article/74848","retrieved":1677044514403},{"title":"세상에서 가장 큰 캔버스  '메종 수잔'","contents":"모든 벽이 자신의 그림으로 가득 찬 나탈리 레테의 별장에 가다.","link":"https://www.elle.co.kr/article/72986","retrieved":1677044514408},{"title":"여백으로 가득 채운 빈 집","contents":"빈틈과 모자람 그리고 일말의 여백이 만든 풍요로움.","link":"https://www.elle.co.kr/article/72985","retrieved":1677044514410},{"title":"공간의 씬 스틸러들 ② 더 프레이즈","contents":"'더 프레이즈'의 페이지는 매 이슈마다 확고한 방점을 찍으며 펼쳐진다.","link":"https://www.elle.co.kr/article/72984","retrieved":1677433322336},{"title":"컬러풀 소파! 그린 & 블루","contents":"싱그러운 에너지를 불어넣는 푸른빛 마법.","link":"https://www.elle.co.kr/article/72983","retrieved":1677433322336}]}