{"title":"엘르 코리아 ─ 스타","url":"https://www.elle.co.kr/star","favicon":"https://www.elle.co.kr/favicon.ico","elements":[{"title":"손흥민과 전지현이 함께? 2023 FW 런던 패션위크 #ELLE쇼타임","contents":"&lt;엘르&gt;팀이 현장에서 직접 보고 느낀 2023 FW 런던 패션위크 취재 일지! #ELLEshowtime","link":"https://www.elle.co.kr/article/75893","retrieved":1679074800473,"image":"https://image.jtbcplus.kr/data/contents/jam_photo/202303/17/aabfb70a-7bfa-4b21-9fee-b99eea7c1d56.gif"},{"title":"방탄소년단 정국이 극찬한 '불그리' 레시피 공개! 지민과 뷔도 관심 보였다는데?","contents":"","link":"https://www.elle.co.kr/article/75889","retrieved":1679074800481,"image":"https://image.jtbcplus.kr/data/contents/jam_photo/202303/17/8c713344-b88f-4a28-9368-5c118ff79d15.jpg"},{"title":"봄은 TXT 로소이다, 범규 태현 <엘르> 화보 공개","contents":"투모로우바이투게더 범규와 태현이 오래된 영화 속 한 장면처럼 마주 앉았다.","link":"https://www.elle.co.kr/article/75884","retrieved":1679074800481,"image":"https://image.jtbcplus.kr/data/contents/jam_photo/202303/17/9ca92953-d484-48f2-8827-966eb4bb7e84.jpg"},{"title":"아이비가 매일 잊지 않고 챙기는 이것! 가방 속 필수 뷰티템 6","contents":"구강 관리 제품부터 피부 보습 아이템까지, 그녀의 취향이 듬뿍 담긴 아이템들을 구경해 보세요...","link":"https://www.elle.co.kr/article/75888","retrieved":1679074800481,"image":"https://image.jtbcplus.kr/data/contents/jam_photo/202303/17/d5fc0d3d-3a57-4df8-ae72-eadb9d69fe8d.jpg"},{"title":"'더 글로리' 전재준으로 인생캐 완성! 박성훈의 최애 운동은 바로 이것? #스타다이어트","contents":"","link":"https://www.elle.co.kr/article/75880","retrieved":1679074800483,"image":"https://image.jtbcplus.kr/data/contents/jam_photo/202303/16/f5e85193-801d-4d91-a4f2-01e8b95926a1.jpg"},{"title":"4년 논란 끝에 개봉하는 '인어공주' 실사 영화, 호불호 격하게 갈리는 까닭","contents":"","link":"https://www.elle.co.kr/article/75876","retrieved":1679031639417,"image":"https://image.jtbcplus.kr/data/contents/jam_photo/202303/16/b5a2cb67-f5a2-40d3-ae5c-ee4a2c020a86.jpg"},{"title":"NEWYORK! 2023 FW 뉴욕 패션위크 #ELLE쇼타임","contents":"배우 박은빈, NCT 쟈니가 찾은 뉴욕.  &lt;엘르&gt;팀이 현장에서 직접 보고 느낀 2023 FW 뉴욕 ...","link":"https://www.elle.co.kr/article/75871","retrieved":1679031639427,"image":"https://image.jtbcplus.kr/data/contents/jam_photo/202303/16/a3124d06-f5cc-454d-aebd-3c0b7d2d217a.gif"},{"title":"봄 데일리 룩으로 딱! <성스러운 아이돌> 고보결 VS <모범택시2> 표예진 #VS드라마패션","contents":"드라마 속 신스틸러로 활약 중인 &lt;성스러운 아이돌&gt;의 고보결과 &lt;모범택시2&gt;의 표예진! 봄맞이 O...","link":"https://www.elle.co.kr/article/75868","retrieved":1679031639428,"image":"https://image.jtbcplus.kr/data/contents/jam_photo/202303/16/e6b03c42-1cd1-4dd4-9a47-62dc040012d9.jpg"}]}